evoaug/__init__.py
evoaug/augment.py
evoaug/evoaug.py
evoaug2-2.0.3.dist-info/licenses/LICENSE
utils/__init__.py
utils/model_zoo.py
utils/utils.py
evoaug2-2.0.3.dist-info/METADATA
evoaug2-2.0.3.dist-info/WHEEL
evoaug2-2.0.3.dist-info/top_level.txt
evoaug2-2.0.3.dist-info/RECORD
