Metadata-Version: 2.4
Name: evoaug2
Version: 2.0.3
Summary: Evolution-Inspired Data Augmentation for Genomic Sequences - DataLoader Version
Home-page: https://github.com/aduranu/evoaug
Author: Peter K. Koo
Author-email: "Peter K. Koo" <koo@cshl.edu>
Maintainer: Peter K. Koo
Maintainer-email: "Peter K. Koo" <koo@cshl.edu>
License: MIT
Project-URL: Homepage, https://github.com/aduranu/evoaug
Project-URL: Repository, https://github.com/aduranu/evoaug
Project-URL: Issues, https://github.com/aduranu/evoaug/issues
Keywords: genomics,data-augmentation,deep-learning,pytorch,bioinformatics
Platform: any
Classifier: Development Status :: 4 - Beta
Classifier: Intended Audience :: Science/Research
Classifier: Intended Audience :: Developers
Classifier: License :: OSI Approved :: MIT License
Classifier: Operating System :: OS Independent
Classifier: Programming Language :: Python :: 3
Classifier: Programming Language :: Python :: 3.8
Classifier: Programming Language :: Python :: 3.9
Classifier: Programming Language :: Python :: 3.10
Classifier: Programming Language :: Python :: 3.11
Classifier: Topic :: Scientific/Engineering :: Bio-Informatics
Classifier: Topic :: Scientific/Engineering :: Artificial Intelligence
Classifier: Topic :: Software Development :: Libraries :: Python Modules
Classifier: Topic :: Software Development :: Libraries
Provides: evoaug2
Requires-Python: >=3.8
License-File: LICENSE
Requires-Dist: torch>=1.9.0
Requires-Dist: pytorch-lightning>=1.5.0
Requires-Dist: numpy>=1.20.0
Requires-Dist: scipy>=1.7.0
Requires-Dist: h5py>=3.1.0
Requires-Dist: scikit-learn>=1.0.0
Provides-Extra: dev
Requires-Dist: pytest>=6.0; extra == "dev"
Requires-Dist: pytest-cov>=2.0; extra == "dev"
Requires-Dist: black>=21.0; extra == "dev"
Requires-Dist: isort>=5.0; extra == "dev"
Requires-Dist: flake8>=3.8; extra == "dev"
Requires-Dist: mypy>=0.800; extra == "dev"
Requires-Dist: pre-commit>=2.15; extra == "dev"
Provides-Extra: examples
Requires-Dist: matplotlib>=3.3; extra == "examples"
Requires-Dist: seaborn>=0.11; extra == "examples"
Requires-Dist: jupyter>=1.0; extra == "examples"
Requires-Dist: ipywidgets>=7.6; extra == "examples"
Provides-Extra: full
Requires-Dist: torch>=1.9.0; extra == "full"
Requires-Dist: pytorch-lightning>=1.5.0; extra == "full"
Requires-Dist: numpy>=1.20.0; extra == "full"
Requires-Dist: scipy>=1.7.0; extra == "full"
Requires-Dist: h5py>=3.1.0; extra == "full"
Requires-Dist: matplotlib>=3.3.0; extra == "full"
Requires-Dist: seaborn>=0.11.0; extra == "full"
Dynamic: author
Dynamic: home-page
Dynamic: license-file
Dynamic: maintainer
Dynamic: platform
Dynamic: provides
Dynamic: requires-python
